aws_artifact_copy/__init__.py
aws_artifact_copy/__main__.py
aws_artifact_copy/cli.py
aws_artifact_copy/common/__init__.py
aws_artifact_copy/common/botocore.py
aws_artifact_copy/common/serialization.py
aws_artifact_copy/services/__init__.py
aws_artifact_copy/services/ebs.py
aws_artifact_copy/services/ecr.py
aws_artifact_copy/services/s3.py
aws_artifact_copy-0.1.0.dist-info/entry_points.txt
aws_artifact_copy-0.1.0.dist-info/LICENSE
aws_artifact_copy-0.1.0.dist-info/WHEEL
aws_artifact_copy-0.1.0.dist-info/METADATA
aws_artifact_copy-0.1.0.dist-info/RECORD
