Metadata-Version: 2.1
Name: aws-artifact-copy
Version: 0.1.0
Summary: 
Author: Chaz Schlarp
Author-email: schlarpc@gmail.com
Requires-Python: >=3.9,<4.0
Classifier: Programming Language :: Python :: 3
Classifier: Programming Language :: Python :: 3.10
Classifier: Programming Language :: Python :: 3.9
Requires-Dist: aiobotocore (>=2.1.0,<3.0.0)
Requires-Dist: trio (>=0.19.0,<0.20.0)
Requires-Dist: trio-asyncio (>=0.12.0,<0.13.0)
